flask_ssm/__init__.py
flask_ssm/logging/__init__.py
flask_ssm/logging/logs_config.py
flask_ssm/pybatis/__init__.py
flask_ssm/pybatis/annotation.py
flask_ssm/springframework/__init__.py
flask_ssm/springframework/boot.py
flask_ssm/springframework/stereotype.py
flask_ssm/springframework/context/__init__.py
flask_ssm/springframework/context/annotation.py
flask_ssm/springframework/scheduling/__init__.py
flask_ssm/springframework/scheduling/annotation.py
flask_ssm/springframework/transaction/__init__.py
flask_ssm/springframework/transaction/annotation.py
flask_ssm/springframework/validation/__init__.py
flask_ssm/springframework/validation/annotation.py
flask_ssm/springframework/web/__init__.py
flask_ssm/springframework/web/bind/__init__.py
flask_ssm/springframework/web/bind/annotation.py
flask_ssm/unittest/__init__.py
flask_ssm/utils/__init__.py
flask_ssm/utils/context_utils.py
flask_ssm/utils/module_utils.py
flask_ssm/utils/time_utils.py
flask_ssm/utils/type_utils.py
flask_ssm/vo/__init__.py
flask_ssm/vo/common.py
flask_ssm-3.10.8.1.dist-info/licenses/LICENSE
flask_ssm-3.10.8.1.dist-info/METADATA
flask_ssm-3.10.8.1.dist-info/WHEEL
flask_ssm-3.10.8.1.dist-info/top_level.txt
flask_ssm-3.10.8.1.dist-info/RECORD
