Metadata-Version: 2.4
Name: Flask-SSM
Version: 3.10.8.1
Summary: A Flask based package imitate with Spring Framework
Home-page: https://github.com/ZongXR/Flask-SSM
Author: Xiangrui Zong
Author-email: zxr@tju.edu.cn
License: GNU General Public License v3 (GPLv3)
Classifier: Intended Audience :: Developers
Classifier: Operating System :: OS Independent
Classifier: Natural Language :: Chinese (Simplified)
Classifier: Programming Language :: Python :: 3
Classifier: Topic :: Software Development :: Libraries
Classifier: License :: OSI Approved :: GNU General Public License v3 (GPLv3)
Requires-Python: >=3.7,<3.11
License-File: LICENSE
Requires-Dist: Flask~=2.3.3
Requires-Dist: Flask-APScheduler>1.12.2,~=1.12.3
Requires-Dist: Flask-Cors~=3.0.10
Requires-Dist: Flask-HTTPAuth~=4.5.0
Requires-Dist: Flask-SQLAlchemy==3.1.1
Requires-Dist: SQLAlchemy~=2.0.41
Requires-Dist: pydantic~=2.0
Requires-Dist: typing-inspect~=0.8.0; python_version == "3.7"
Requires-Dist: APScheduler==3.10.4
Requires-Dist: Werkzeug<=2.3.8,>=2.1.2
Requires-Dist: sqlglot
Dynamic: author
Dynamic: author-email
Dynamic: classifier
Dynamic: description
Dynamic: description-content-type
Dynamic: home-page
Dynamic: license
Dynamic: license-file
Dynamic: requires-dist
Dynamic: requires-python
Dynamic: summary
